aiohttp_api_client/__init__.py
aiohttp_api_client/json_api.py
aiohttp_api_client-0.2.0.dist-info/WHEEL
aiohttp_api_client-0.2.0.dist-info/METADATA
aiohttp_api_client-0.2.0.dist-info/RECORD
