Metadata-Version: 2.1
Name: aiohttp-api-client
Version: 0.2.0
Summary: aiohttp based api client
Home-page: https://github.com/xppt/py-aiohttp-api-client
Author: xppt
Author-email: 21246102+xppt@users.noreply.github.com
Requires-Python: >=3.6,<4.0
Classifier: Programming Language :: Python :: 3
Classifier: Programming Language :: Python :: 3.6
Classifier: Programming Language :: Python :: 3.7
Classifier: Programming Language :: Python :: 3.8
Classifier: Programming Language :: Python :: 3.9
Requires-Dist: aiohttp (>=3,<4)
